.bumpversion.cfg
CONTRIBUTING.md
LICENSE
MANIFEST.in
Makefile
README.md
pyproject.toml
setup.py
source/methods.py
source/tests/__init__.py
source/tests/data.csv
source/tests/test_all.py
spending_habits_tracker.egg-info/PKG-INFO
spending_habits_tracker.egg-info/SOURCES.txt
spending_habits_tracker.egg-info/dependency_links.txt
spending_habits_tracker.egg-info/requires.txt
spending_habits_tracker.egg-info/top_level.txt