Metadata-Version: 2.1
Name: spending-habits-tracker
Version: 0.1.0
Summary: Spending-Habits-Tracker is a Python library to provide real-time data of a user's spending habits.
Author-email: Unal Yigit Ozulku <uyozulku@gmail.com>
License:                                  Apache License
Project-URL: repository, https://github.com/uyozulku/spending-habits-tracker
Classifier: Development Status :: 2 - Pre-Alpha
Classifier: Programming Language :: Python :: Implementation :: CPython
Classifier: Programming Language :: Python :: Implementation :: PyPy
Classifier: Programming Language :: Python :: 3
Classifier: Programming Language :: Python :: 3.7
Classifier: Programming Language :: Python :: 3.8
Classifier: Programming Language :: Python :: 3.9
Classifier: Programming Language :: Python :: 3.10
Classifier: Programming Language :: Python :: 3.11
Requires-Python: >=3.7
Provides-Extra: develop
License-File: LICENSE
